MANIFEST.in
README.rst
setup.py
rabbitmq_alert.egg-info/PKG-INFO
rabbitmq_alert.egg-info/SOURCES.txt
rabbitmq_alert.egg-info/dependency_links.txt
rabbitmq_alert.egg-info/entry_points.txt
rabbitmq_alert.egg-info/top_level.txt
rabbitmqalert/__init__.py
rabbitmqalert/apiclient.py
rabbitmqalert/argumentsparser.py
rabbitmqalert/conditionchecker.py
rabbitmqalert/logger.py
rabbitmqalert/notifier.py
rabbitmqalert/rabbitmqalert.py
rabbitmqalert/config/config.ini.example
rabbitmqalert/config/service/rabbitmq-alert
rabbitmqalert/config/service/rabbitmq-alert.service
rabbitmqalert/models/__init__.py
rabbitmqalert/models/argument.py