Metadata-Version: 1.1
Name: rabbitmq-alert
Version: 1.8.0
Summary: Send notifications when predefined conditions are met
Home-page: https://github.com/gfronza/rabbitmq-alert
Author: Germano Fronza (gfronza), Kostas Milonas (mylk), velika12, Robert Kopaczewski (23doors), Ivan Timeev (TeslA1402), Anderson Diego Kulpa Fachini (anderson-fachini)
Author-email: germano.inf@gmail.com
License: UNKNOWN
Download-URL: https://github.com/gfronza/rabbitmq-alert/tarball/1.8.0
Keywords: rabbitmq,alert,monitor
Platform: UNKNOWN
